sentry_jsonnet/__init__.py
sentry_jsonnet/py.typed
sentry_jsonnet-0.0.5.dist-info/METADATA
sentry_jsonnet-0.0.5.dist-info/WHEEL
sentry_jsonnet-0.0.5.dist-info/top_level.txt
sentry_jsonnet-0.0.5.dist-info/RECORD
